{"track": {"album": {"@attr": {"position": "8"}, "title": "Criss-Cross", "url": "http://www.last.fm/music/Thelonious+Monk/Criss-Cross", "image": [{"#text": "http://userserve-ak.last.fm/serve/64s/70825194.png", "size": "small"}, {"#text": "http://userserve-ak.last.fm/serve/126/70825194.png", "size": "medium"}, {"#text": "http://userserve-ak.last.fm/serve/174s/70825194.png", "size": "large"}, {"#text": "http://userserve-ak.last.fm/serve/300x300/70825194.png", "size": "extralarge"}], "artist": "Thelonious Monk", "mbid": "1c59f8d0-fbe3-4ffc-98e5-e64b69576708"}, "streamable": {"#text": "0", "fulltrack": "0"}, "name": "Crepuscule With Nellie", "artist": {"url": "http://www.last.fm/music/Thelonious+Monk", "mbid": "70105dc4-9881-4e99-b470-dbb5a01674d9", "name": "Thelonious Monk"}, "url": "http://www.last.fm/music/Thelonious+Monk/_/Crepuscule+With+Nellie", "listeners": "38506", "comments": ["TOOK ME A WHILE TO GET MONK I NOW REALIZE THE MAN IS A TRUE JAZZ MASTER", "Such a beautiful and odd tune....", "behind every great black man is the police", "Behind a genius, there's always a strong woman.", "Monk travels well...sounds even better wherever dengue fever rules... a quirky balm...", "Monk Monk Monk.  whew.  genius. \r\n\r\nJazz Lives!!", "Isn't this the live version off the Town Hall Concert album? It's a thing of skewed beauty, wherever it's from....", "mmmonk", "SAVE A STREET ANIMAL PLEASE", "o monge do sax, fator 0 do instrumento e a goma em ess\u00eancia!", "monk \u00e9 soment monk... inigualavel", "sencillamente es fabulosa la musica de este disco, el saxo!!, fabuloso"], "toptags": {"tag": [{"url": "http://www.last.fm/tag/jazz", "name": "jazz"}, {"url": "http://www.last.fm/tag/bebop", "name": "bebop"}, {"url": "http://www.last.fm/tag/piano", "name": "piano"}, {"url": "http://www.last.fm/tag/thelonious%20monk", "name": "thelonious monk"}, {"url": "http://www.last.fm/tag/drjazzmrfunkmusic", "name": "drjazzmrfunkmusic"}]}, "mbid": "2e724b8a-eef7-49d1-9235-e0a78eb308db", "duration": "274000", "playcount": "92835", "id": "1312106"}}