{"track": {"album": {"@attr": {"position": "16"}, "title": "Real Gone", "url": "http://www.last.fm/music/Tom+Waits/Real+Gone", "image": [{"#text": "http://userserve-ak.last.fm/serve/64s/87363013.png", "size": "small"}, {"#text": "http://userserve-ak.last.fm/serve/126/87363013.png", "size": "medium"}, {"#text": "http://userserve-ak.last.fm/serve/174s/87363013.png", "size": "large"}, {"#text": "http://userserve-ak.last.fm/serve/300x300/87363013.png", "size": "extralarge"}], "artist": "Tom Waits", "mbid": "1ab682c6-03f6-3e9c-b07f-94df7bb04efb"}, "streamable": {"#text": "0", "fulltrack": "0"}, "name": "Make It Rain", "artist": {"url": "http://www.last.fm/music/Tom+Waits", "mbid": "c3aeb863-7b26-4388-94e8-5a240f2be21b", "name": "Tom Waits"}, "url": "http://www.last.fm/music/Tom+Waits/_/Make+It+Rain", "listeners": "60980", "comments": ["Ribot and Waits make a great combo!", "lol davy. he says make it rain like 100 times in the song. its DEFINITELY called chick a boom and not make it rain right", "That means you tagged it wrong Davy.", "Fuck me like that.", "This is Chick-A-Boom, not Make it Rain", "Hell of a song! A simple but strong groove and an awesome voice!!! Just great :-)", "a little rain never hurt no one", "8:54 version from Atlanta beats everything", "It's playing the bonus track of Real Gone instead of Make it Rain right now...", "The Glitter and Doom version of this kinda obliterates the studio one", "Make It Rain (1:17). 3:40 on mine.", "It's the same old world, but nothing looks the same", "This is one of the best blues songs i've ever heard.", "Night's too quiet - stretched out alone. I need the whif of thunder and the wind's dark moan.", "You know the story, here it comes again!\n\nAh, but we love to hear you tell it Tom.", "I'm not Abel, I'm just Cain.", "yeah and solo is fucking amazing :)", "ribot on guitar......hero", "That bitch took all my money.", "i want to believe in the mercy of the world again!"], "toptags": {"tag": [{"url": "http://www.last.fm/tag/blues", "name": "blues"}, {"url": "http://www.last.fm/tag/alternative", "name": "alternative"}, {"url": "http://www.last.fm/tag/singer-songwriter", "name": "singer-songwriter"}, {"url": "http://www.last.fm/tag/tom%20waits", "name": "tom waits"}, {"url": "http://www.last.fm/tag/folk", "name": "folk"}]}, "mbid": "9a694626-f6ae-4f99-bcf6-7e8dc7669430", "duration": "219000", "playcount": "258034", "id": "7995987"}}