{"track": {"album": {"@attr": {"position": "11"}, "title": "The Suburbs", "url": "http://www.last.fm/music/Arcade+Fire/The+Suburbs", "image": [{"#text": "http://userserve-ak.last.fm/serve/64s/50128417.png", "size": "small"}, {"#text": "http://userserve-ak.last.fm/serve/126/50128417.png", "size": "medium"}, {"#text": "http://userserve-ak.last.fm/serve/174s/50128417.png", "size": "large"}, {"#text": "http://userserve-ak.last.fm/serve/300x300/50128417.png", "size": "extralarge"}], "artist": "Arcade Fire", "mbid": "1cf9ad6c-ae66-333f-9690-604daca42564"}, "streamable": {"#text": "0", "fulltrack": "0"}, "name": "Wasted Hours", "artist": {"url": "http://www.last.fm/music/Arcade+Fire", "mbid": "52074ba6-e495-4ef3-9bb4-0703888a9f68", "name": "Arcade Fire"}, "url": "http://www.last.fm/music/Arcade+Fire/_/Wasted+Hours", "listeners": "280538", "comments": ["sad and lovely", "<3 from Modesto CA", "It reminds me of a cross between The Beatles' \"In My Life\" and the high points of Bon Iver's mellow folk.", "Arcade Fire I will give you a $1 if you come to Springfield. Please go on tour.  I have been waiting a long time.", "is this rock!?", "\"Wasted hours that you made new and turned into a life that we could live. Wishing you were anywhere but here. You watched the life you're living disappear. And now I see, we're still kids in buses longing to be free\" God, these lyrics get me everytime. This song makes me feel so good inside.", "Wasted hours before we knew where to go or what to do...", "Reminds me of \"Wimoweh.\"", "I think I know very well what this song is about", "Reminds me of \"California Girls\" by The Beach Boys", "Deluxe Version is the best.", "seriously one of the best songs ever", "Am I the only one who doesn't like this song?", "The story of my fucking life, lol.", "Oh man, love the new version!", "new version is so amazing <3", "DELUXE EDITION VERSION <3", "These lyrics... THESE LYRICS!", "This song just keeps and keeps growing in me. The best of the album. There, I said it.", "Wasted hours before we knew where to go and what to do. Wasted hours that you made new and turned into a life that we can live."], "toptags": {"tag": [{"url": "http://www.last.fm/tag/rock", "name": "rock"}, {"url": "http://www.last.fm/tag/indie%20rock", "name": "indie rock"}, {"url": "http://www.last.fm/tag/indie", "name": "indie"}, {"url": "http://www.last.fm/tag/canadian", "name": "canadian"}, {"url": "http://www.last.fm/tag/alternative", "name": "alternative"}]}, "mbid": "00101edd-3a4f-47eb-aac1-767584291e0a", "duration": "199000", "playcount": "1705115", "id": "423297500"}}