{"track": {"album": {"@attr": {"position": "11"}, "title": "Memento", "url": "http://www.last.fm/music/Booka+Shade/Memento", "image": [{"#text": "http://userserve-ak.last.fm/serve/64s/33490707.jpg", "size": "small"}, {"#text": "http://userserve-ak.last.fm/serve/126/33490707.jpg", "size": "medium"}, {"#text": "http://userserve-ak.last.fm/serve/174s/33490707.jpg", "size": "large"}, {"#text": "http://userserve-ak.last.fm/serve/300x300/33490707.jpg", "size": "extralarge"}], "artist": "Booka Shade", "mbid": "7878a370-d328-45e3-bd1a-d8c0003dfba2"}, "streamable": {"#text": "1", "fulltrack": "0"}, "name": "Cha!", "artist": {"url": "http://www.last.fm/music/Booka+Shade", "mbid": "98f068ed-66ee-4f8f-a0be-9c763ceb7ef2", "name": "Booka Shade"}, "url": "http://www.last.fm/music/Booka+Shade/_/Cha!", "listeners": "16041", "comments": [], "toptags": {"tag": [{"url": "http://www.last.fm/tag/techno", "name": "techno"}, {"url": "http://www.last.fm/tag/minimal", "name": "minimal"}, {"url": "http://www.last.fm/tag/electronic", "name": "electronic"}, {"url": "http://www.last.fm/tag/house", "name": "house"}, {"url": "http://www.last.fm/tag/electro", "name": "electro"}]}, "mbid": "5d7a5afb-6824-42b3-8633-640084ae50e2", "duration": "228000", "playcount": "43076", "id": "9669621"}}