{"streamable": {"#text": "1", "fulltrack": "0"}, "@attr": {"rank": "681"}, "name": "I'm Not A Player", "artist": {"url": "http://www.last.fm/music/Big+Punisher", "mbid": "4b0a3b93-6aeb-45e6-8137-31c9e881cce1", "name": "Big Punisher"}, "url": "http://www.last.fm/music/Big+Punisher/_/I%27m+Not+A+Player", "image": [{"#text": "http://userserve-ak.last.fm/serve/34s/56871071.png", "size": "small"}, {"#text": "http://userserve-ak.last.fm/serve/64s/56871071.png", "size": "medium"}, {"#text": "http://userserve-ak.last.fm/serve/126/56871071.png", "size": "large"}, {"#text": "http://userserve-ak.last.fm/serve/300x300/56871071.png", "size": "extralarge"}], "mbid": "f046b77b-a935-4768-b60a-0e70ee9c7303", "duration": "221"}