{"track": {"album": {"@attr": {"position": "47"}, "title": "India, World", "url": "http://www.last.fm/music/Various+Artists/India,+World", "image": [{"#text": "http://userserve-ak.last.fm/serve/64s/63821035.jpg", "size": "small"}, {"#text": "http://userserve-ak.last.fm/serve/126/63821035.jpg", "size": "medium"}, {"#text": "http://userserve-ak.last.fm/serve/174s/63821035.jpg", "size": "large"}, {"#text": "http://userserve-ak.last.fm/serve/300x300/63821035.jpg", "size": "extralarge"}], "artist": "Various Artists", "mbid": "999d85fe-67dd-4426-a241-69ac5a71d9c1"}, "streamable": {"#text": "1", "fulltrack": "0"}, "name": "Song For Raja 2", "artist": {"url": "http://www.last.fm/music/Lucy+Francis", "mbid": "3a657118-15e7-4b7c-b100-e98f32087558", "name": "Lucy Francis"}, "url": "http://www.last.fm/music/Lucy+Francis/_/Song+For+Raja+2", "listeners": "8", "toptags": "\n      ", "mbid": "", "duration": "200000", "playcount": "18", "id": "57311181"}}