{"streamable": {"#text": "0", "fulltrack": "0"}, "@attr": {"rank": "561"}, "name": "Holiday Song", "artist": {"url": "http://www.last.fm/music/She+Wants+Revenge", "mbid": "f434ae2b-b203-490d-a8ac-aa9cd51c0e73", "name": "She Wants Revenge"}, "url": "http://www.last.fm/music/She+Wants+Revenge/_/Holiday+Song", "image": [{"#text": "http://userserve-ak.last.fm/serve/34s/90814085.png", "size": "small"}, {"#text": "http://userserve-ak.last.fm/serve/64s/90814085.png", "size": "medium"}, {"#text": "http://userserve-ak.last.fm/serve/126/90814085.png", "size": "large"}, {"#text": "http://userserve-ak.last.fm/serve/300x300/90814085.png", "size": "extralarge"}], "mbid": "22a5bac3-6d31-4f4c-9546-8641ed9817f3", "duration": "232"}