{"track": {"album": {"@attr": {"position": "9"}, "title": "Teenage Dream", "url": "http://www.last.fm/music/Katy+Perry/Teenage+Dream", "image": [{"#text": "http://userserve-ak.last.fm/serve/64s/92013903.png", "size": "small"}, {"#text": "http://userserve-ak.last.fm/serve/126/92013903.png", "size": "medium"}, {"#text": "http://userserve-ak.last.fm/serve/174s/92013903.png", "size": "large"}, {"#text": "http://userserve-ak.last.fm/serve/300x300/92013903.png", "size": "extralarge"}], "artist": "Katy Perry", "mbid": "2356f510-d5ae-4cac-aa15-3d2db95b684c"}, "wiki": {"content": "Perry started of her music career as a gospel-rock artist under the name of Katy Hudson. The singer's Christian back story crops up in this song where she references the Old Testament account of Queen Esther, a Jewish orphan who married a Persian king and uncovered a plot to exterminate the Jews.\n        \nUser-contributed text is available under the Creative Commons By-SA License and may also be available under the GNU FDL.", "summary": "Perry started of her music career as a gospel-rock artist under the name of Katy Hudson. The singer's Christian back story crops up in this song where she references the Old Testament account of Queen Esther, a Jewish orphan who married a Persian king and uncovered a plot to exterminate the Jews.", "published": "Sat, 5 Feb 2011 12:49:26 +0000"}, "streamable": {"#text": "0", "fulltrack": "0"}, "name": "Who Am I Living For?", "artist": {"url": "http://www.last.fm/music/Katy+Perry", "mbid": "122d63fc-8671-43e4-9752-34e846d62a9c", "name": "Katy Perry"}, "url": "http://www.last.fm/music/Katy+Perry/_/Who+Am+I+Living+For%3F", "listeners": "194897", "toptags": {"tag": [{"url": "http://www.last.fm/tag/pop", "name": "pop"}, {"url": "http://www.last.fm/tag/katy%20perry", "name": "katy perry"}, {"url": "http://www.last.fm/tag/female%20vocalists", "name": "female vocalists"}, {"url": "http://www.last.fm/tag/teenage%20dream", "name": "teenage dream"}, {"url": "http://www.last.fm/tag/electropop", "name": "electropop"}]}, "mbid": "182defde-f578-4f62-87f7-cb02468ff560", "duration": "249000", "playcount": "1130201", "id": "426416867"}}