{"track": {"album": {"@attr": {"position": "13"}, "title": "Who You Are", "url": "http://www.last.fm/music/Jessie+J/Who+You+Are", "image": [{"#text": "http://userserve-ak.last.fm/serve/64s/59989281.png", "size": "small"}, {"#text": "http://userserve-ak.last.fm/serve/126/59989281.png", "size": "medium"}, {"#text": "http://userserve-ak.last.fm/serve/174s/59989281.png", "size": "large"}, {"#text": "http://userserve-ak.last.fm/serve/300x300/59989281.png", "size": "extralarge"}], "artist": "Jessie J", "mbid": ""}, "wiki": {"content": "According to the <a href=\"http://www.songfacts.com/detail.php?id=21600\" rel=\"nofollow\">Who You Are Songfacts</a>, Cornish wrote this self-help ballad at the end of a lonely three-month trip to Los Angeles when she was 20. Having been shunted from studio to studio with various producers she was ready to pack it all in. She told The Independent December 10, 2010: &quot;I'm very much someone that lives to be happy. It's not just about the parties and I know so-and-so \u2013 I'm not that girl. So I looked in the mirror and started to cry and said 'who am I?' Music is my therapy.&quot;\n \n &quot;Who You Are&quot; was released first as a promotional single and peaked at #86 on the Australian Singles Chart, #40 on UK Singles Chart and #85 on the Canadian Hot 100. In November, &quot;Who You Are&quot; was released as the fifth single from her debut album in the UK. It peaked at #8 on the UK Singles Chart making it Jessie J's fourth top-ten single in the United Kingdom. The single has been silver certified by the BPI.\n        \nUser-contributed text is available under the Creative Commons By-SA License and may also be available under the GNU FDL.", "summary": "According to the <a href=\"http://www.songfacts.com/detail.php?id=21600\" rel=\"nofollow\">Who You Are Songfacts</a>, Cornish wrote this self-help ballad at the end of a lonely three-month trip to Los Angeles when she was 20. Having been shunted from studio to studio with various producers she was ready to pack it all in. She told The Independent December 10, 2010: &quot;I'm very much someone that lives to be happy. It's not just about the parties and I know so-and-so \u2013 I'm not that girl. So I looked in the mirror and started to cry and said 'who am I?' Music is my therapy.&quot;  ", "published": "Sat, 2 Feb 2013 02:35:18 +0000"}, "streamable": {"#text": "0", "fulltrack": "0"}, "name": "Who You Are", "artist": {"url": "http://www.last.fm/music/Jessie+J", "mbid": "d24fb461-dee8-41fc-bb15-2f13bb2644a6", "name": "Jessie J"}, "url": "http://www.last.fm/music/Jessie+J/_/Who+You+Are", "listeners": "196453", "toptags": {"tag": [{"url": "http://www.last.fm/tag/pop", "name": "pop"}, {"url": "http://www.last.fm/tag/jessie%20j", "name": "jessie j"}, {"url": "http://www.last.fm/tag/female%20vocalists", "name": "female vocalists"}, {"url": "http://www.last.fm/tag/soul", "name": "soul"}, {"url": "http://www.last.fm/tag/10s", "name": "10s"}]}, "mbid": "2817d5bb-fdf5-4f9e-8127-5e56a32a8801", "duration": "231000", "playcount": "1122176", "id": "440048826"}}