{"album": {"name": "Pyro Technics", "artist": "DJ Rectangle", "url": "http://www.last.fm/music/DJ+Rectangle/Pyro+Technics", "image": [{"#text": "http://userserve-ak.last.fm/serve/34s/78290134.png", "size": "small"}, {"#text": "http://userserve-ak.last.fm/serve/64s/78290134.png", "size": "medium"}, {"#text": "http://userserve-ak.last.fm/serve/174s/78290134.png", "size": "large"}, {"#text": "http://userserve-ak.last.fm/serve/300x300/78290134.png", "size": "extralarge"}, {"#text": "http://userserve-ak.last.fm/serve/_/78290134/Pyro+Technics+PNG.png", "size": "mega"}], "listeners": "316709", "toptags": {"tag": {"url": "http://www.last.fm/tag/rap", "name": "rap"}}, "releasedate": "    30 Nov 2004, 00:00", "mbid": "36ba68ce-43a0-45d6-a5e9-38f7da3ed71b", "tracks": {"track": [{"streamable": {"#text": "0", "fulltrack": "0"}, "@attr": {"rank": "1"}, "name": "Intro", "artist": {"url": "http://www.last.fm/music/DJ+Rectangle", "mbid": "901fc9df-8e2f-4d9c-8e5a-d9b67afc7823", "name": "DJ Rectangle"}, "url": "http://www.last.fm/music/DJ+Rectangle/_/Intro", "mbid": "047c0d78-7913-4f17-a43c-f5a44083aac1", "duration": "93"}, {"streamable": {"#text": "0", "fulltrack": "0"}, "@attr": {"rank": "2"}, "name": "Put You On The Game", "artist": {"url": "http://www.last.fm/music/The+Game", "mbid": "ab91c554-63b8-44b3-bba7-042f2942c896", "name": "The Game"}, "url": "http://www.last.fm/music/The+Game/_/Put+You+On+The+Game", "mbid": "1b502447-b371-42a9-b189-9e4ee730d666", "duration": "254"}, {"streamable": {"#text": "0", "fulltrack": "0"}, "@attr": {"rank": "3"}, "name": "Bottle Rocket Scratch", "artist": {"url": "http://www.last.fm/music/DJ+Rectangle", "mbid": "901fc9df-8e2f-4d9c-8e5a-d9b67afc7823", "name": "DJ Rectangle"}, "url": "http://www.last.fm/music/DJ+Rectangle/_/Bottle+Rocket+Scratch", "mbid": "662182b7-b456-486b-99df-39ffcb581918", "duration": "22"}, {"streamable": {"#text": "0", "fulltrack": "0"}, "@attr": {"rank": "4"}, "name": "Like A Boss", "artist": {"url": "http://www.last.fm/music/Slim+Thug", "mbid": "e0f5273c-637e-4e10-8304-81f2f9a31523", "name": "Slim Thug"}, "url": "http://www.last.fm/music/Slim+Thug/_/Like+A+Boss", "mbid": "e105958d-4c5a-458c-a102-60c6e720308c", "duration": "249"}, {"streamable": {"#text": "0", "fulltrack": "0"}, "@attr": {"rank": "5"}, "name": "Exploding Thug Scratch", "artist": {"url": "http://www.last.fm/music/DJ+Rectangle", "mbid": "901fc9df-8e2f-4d9c-8e5a-d9b67afc7823", "name": "DJ Rectangle"}, "url": "http://www.last.fm/music/DJ+Rectangle/_/Exploding+Thug+Scratch", "mbid": "096c58da-4703-4027-838c-2e83529d8de3", "duration": "23"}, {"streamable": {"#text": "0", "fulltrack": "0"}, "@attr": {"rank": "6"}, "name": "D.O. Double G", "artist": {"url": "http://www.last.fm/music/Snoop+Dogg", "mbid": "17d17695-f0e1-46fd-815f-bf577cc5f50d", "name": "Snoop Dogg"}, "url": "http://www.last.fm/music/Snoop+Dogg/_/D.O.+Double+G", "mbid": "b12f8c81-a825-4d30-8db6-b35a30a2c454", "duration": "81"}, {"streamable": {"#text": "0", "fulltrack": "0"}, "@attr": {"rank": "7"}, "name": "B*L*E*N*D (Scarface vs. Nelly)", "artist": {"url": "http://www.last.fm/music/DJ+Rectangle", "mbid": "901fc9df-8e2f-4d9c-8e5a-d9b67afc7823", "name": "DJ Rectangle"}, "url": "http://www.last.fm/music/DJ+Rectangle/_/B*L*E*N*D+(Scarface+vs.+Nelly)", "mbid": "4ee5dd29-64a7-4b68-b6a1-60525d02ee3b", "duration": "32"}, {"streamable": {"#text": "0", "fulltrack": "0"}, "@attr": {"rank": "8"}, "name": "Na-Na-Na-Na (feat. Jazze Pha)", "artist": {"url": "http://www.last.fm/music/Nelly", "mbid": "1475e497-d820-44e7-afab-d80d74277501", "name": "Nelly"}, "url": "http://www.last.fm/music/Nelly/_/Na-Na-Na-Na+(feat.+Jazze+Pha)", "mbid": "0f186cee-d4e3-4378-badb-ef375660c450", "duration": "77"}, {"streamable": {"#text": "0", "fulltrack": "0"}, "@attr": {"rank": "9"}, "name": "Hazardous Materials Scratch", "artist": {"url": "http://www.last.fm/music/DJ+Rectangle", "mbid": "901fc9df-8e2f-4d9c-8e5a-d9b67afc7823", "name": "DJ Rectangle"}, "url": "http://www.last.fm/music/DJ+Rectangle/_/Hazardous+Materials+Scratch", "mbid": "19572343-59d8-4160-989a-4542c4d81b27", "duration": "33"}, {"streamable": {"#text": "0", "fulltrack": "0"}, "@attr": {"rank": "10"}, "name": "I'm A Hustla", "artist": {"url": "http://www.last.fm/music/Cassidy", "mbid": "32090ac9-6e46-47c5-b9ce-69c504a4a7bc", "name": "Cassidy"}, "url": "http://www.last.fm/music/Cassidy/_/I%27m+A+Hustla", "mbid": "d7849a6c-6160-42a8-9b73-ebee8ccbea30", "duration": "245"}, {"streamable": {"#text": "0", "fulltrack": "0"}, "@attr": {"rank": "11"}, "name": "Short Fuse Scratch", "artist": {"url": "http://www.last.fm/music/DJ+Rectangle", "mbid": "901fc9df-8e2f-4d9c-8e5a-d9b67afc7823", "name": "DJ Rectangle"}, "url": "http://www.last.fm/music/DJ+Rectangle/_/Short+Fuse+Scratch", "mbid": "5c94b2da-5e06-4e05-b044-33365d9d8b55", "duration": "42"}, {"streamable": {"#text": "0", "fulltrack": "0"}, "@attr": {"rank": "12"}, "name": "Hold You Down", "artist": {"url": "http://www.last.fm/music/The+Alchemist", "mbid": "03f3deb7-0419-4bf9-a1e7-511946385717", "name": "The Alchemist"}, "url": "http://www.last.fm/music/The+Alchemist/_/Hold+You+Down", "mbid": "15388626-65ea-4b62-a0d3-8c6086d40b68", "duration": "89"}, {"streamable": {"#text": "0", "fulltrack": "0"}, "@attr": {"rank": "13"}, "name": "Flash Powder Scratch", "artist": {"url": "http://www.last.fm/music/DJ+Rectangle", "mbid": "901fc9df-8e2f-4d9c-8e5a-d9b67afc7823", "name": "DJ Rectangle"}, "url": "http://www.last.fm/music/DJ+Rectangle/_/Flash+Powder+Scratch", "mbid": "92fe6522-320c-484f-ba2b-6e04ecf473ed", "duration": "20"}, {"streamable": {"#text": "0", "fulltrack": "0"}, "@attr": {"rank": "14"}, "name": "Intro", "artist": {"url": "http://www.last.fm/music/Ludacris", "mbid": "0638ba22-040f-438d-83a5-9b670c4adaf5", "name": "Ludacris"}, "url": "http://www.last.fm/music/Ludacris/_/Intro", "mbid": "c36c18a3-d9e8-410e-8f49-f528a0ab8a64", "duration": "15"}, {"streamable": {"#text": "0", "fulltrack": "0"}, "@attr": {"rank": "15"}, "name": "Drop It Like It's Hot", "artist": {"url": "http://www.last.fm/music/Snoop+Dogg", "mbid": "17d17695-f0e1-46fd-815f-bf577cc5f50d", "name": "Snoop Dogg"}, "url": "http://www.last.fm/music/Snoop+Dogg/_/Drop+It+Like+It%27s+Hot", "mbid": "8ea58071-b397-4ceb-ac68-abc2b8dae381", "duration": "266"}, {"streamable": {"#text": "0", "fulltrack": "0"}, "@attr": {"rank": "16"}, "name": "Flash Firebomb Scratch", "artist": {"url": "http://www.last.fm/music/DJ+Rectangle", "mbid": "901fc9df-8e2f-4d9c-8e5a-d9b67afc7823", "name": "DJ Rectangle"}, "url": "http://www.last.fm/music/DJ+Rectangle/_/Flash+Firebomb+Scratch", "mbid": "8ece6088-4c1c-46c2-88d8-b97407fa0dbe", "duration": "22"}, {"streamable": {"#text": "0", "fulltrack": "0"}, "@attr": {"rank": "17"}, "name": "Us Against the World (feat. 2pac)", "artist": {"url": "http://www.last.fm/music/Lil%27+Easy", "mbid": "fb25fc94-a295-4d6c-9dc8-512fa4d3373b", "name": "Lil' Easy"}, "url": "http://www.last.fm/music/Lil%27+Easy/_/Us+Against+the+World+(feat.+2pac)", "mbid": "514a65c7-75da-4989-a5cc-fdce1ce9a153", "duration": "132"}, {"streamable": {"#text": "0", "fulltrack": "0"}, "@attr": {"rank": "18"}, "name": "Popshots", "artist": {"url": "http://www.last.fm/music/Ol%27+Dirty+Bastard", "mbid": "", "name": "Ol' Dirty Bastard"}, "url": "http://www.last.fm/music/Ol%27+Dirty+Bastard/_/Popshots", "mbid": "7aa22864-f8f3-45f5-9f67-4a0246949b8f", "duration": "95"}, {"streamable": {"#text": "0", "fulltrack": "0"}, "@attr": {"rank": "19"}, "name": "What's The Problem?", "artist": {"url": "http://www.last.fm/music/Xzibit", "mbid": "9e839dc3-55f3-4492-ad0e-a1a2e84275e2", "name": "Xzibit"}, "url": "http://www.last.fm/music/Xzibit/_/What%27s+The+Problem%3F", "mbid": "13b31ba4-980d-4b38-875a-0edce88a509e", "duration": "150"}, {"streamable": {"#text": "0", "fulltrack": "0"}, "@attr": {"rank": "20"}, "name": "Can I Get A Flicc Witchu (feat. Bootsy Collins)", "artist": {"url": "http://www.last.fm/music/Snoop+Dogg", "mbid": "17d17695-f0e1-46fd-815f-bf577cc5f50d", "name": "Snoop Dogg"}, "url": "http://www.last.fm/music/Snoop+Dogg/_/Can+I+Get+A+Flicc+Witchu+(feat.+Bootsy+Collins)", "mbid": "3f41a727-dbab-4587-a3ce-5701ab2feea7", "duration": "181"}, {"streamable": {"#text": "0", "fulltrack": "0"}, "@attr": {"rank": "21"}, "name": "It's Like That", "artist": {"url": "http://www.last.fm/music/Mariah+Carey", "mbid": "494e8d09-f85b-4543-892f-a5096aed1cd4", "name": "Mariah Carey"}, "url": "http://www.last.fm/music/Mariah+Carey/_/It%27s+Like+That", "mbid": "48c55150-d610-4fd9-8977-e586fe602119", "duration": "202"}, {"streamable": {"#text": "0", "fulltrack": "0"}, "@attr": {"rank": "22"}, "name": "How We Do R*E*M*I*X", "artist": {"url": "http://www.last.fm/music/The+Game", "mbid": "ab91c554-63b8-44b3-bba7-042f2942c896", "name": "The Game"}, "url": "http://www.last.fm/music/The+Game/_/How+We+Do+R*E*M*I*X", "mbid": "7a8db3ae-c5d9-484b-a1a1-b6df707fb47d", "duration": "40"}, {"streamable": {"#text": "0", "fulltrack": "0"}, "@attr": {"rank": "23"}, "name": "Gasolina (Dirty South R*E*M*I*X)", "artist": {"url": "http://www.last.fm/music/Daddy+Yankee", "mbid": "2f522f5c-111c-4ce8-8bd0-d82e97c227ad", "name": "Daddy Yankee"}, "url": "http://www.last.fm/music/Daddy+Yankee/_/Gasolina+(Dirty+South+R*E*M*I*X)", "mbid": "c08401ef-0168-49f0-a3ab-37ed646c9fb0", "duration": "100"}, {"streamable": {"#text": "0", "fulltrack": "0"}, "@attr": {"rank": "24"}, "name": "Pyro Maniac Scratch", "artist": {"url": "http://www.last.fm/music/DJ+Rectangle", "mbid": "901fc9df-8e2f-4d9c-8e5a-d9b67afc7823", "name": "DJ Rectangle"}, "url": "http://www.last.fm/music/DJ+Rectangle/_/Pyro+Maniac+Scratch", "mbid": "511addeb-9844-452a-836e-2878b936f17a", "duration": "21"}, {"streamable": {"#text": "0", "fulltrack": "0"}, "@attr": {"rank": "25"}, "name": "Disco Inferno", "artist": {"url": "http://www.last.fm/music/50+Cent", "mbid": "8e68819d-71be-4e7d-b41d-f1df81b01d3f", "name": "50 Cent"}, "url": "http://www.last.fm/music/50+Cent/_/Disco+Inferno", "mbid": "ebd738e5-9047-4683-b27d-d64575d457ee", "duration": "214"}, {"streamable": {"#text": "0", "fulltrack": "0"}, "@attr": {"rank": "26"}, "name": "Flaming Inferno Scratch", "artist": {"url": "http://www.last.fm/music/DJ+Rectangle", "mbid": "901fc9df-8e2f-4d9c-8e5a-d9b67afc7823", "name": "DJ Rectangle"}, "url": "http://www.last.fm/music/DJ+Rectangle/_/Flaming+Inferno+Scratch", "mbid": "8fd3b828-e21a-4abe-bf71-0c768b4d4961", "duration": "21"}, {"streamable": {"#text": "0", "fulltrack": "0"}, "@attr": {"rank": "27"}, "name": "Get Right (feat. J-Lo)", "artist": {"url": "http://www.last.fm/music/Fabolous", "mbid": "d2299099-e617-46dd-b013-ba0b4c72bc63", "name": "Fabolous"}, "url": "http://www.last.fm/music/Fabolous/_/Get+Right+(feat.+J-Lo)", "mbid": "02bb29f2-27fa-45f7-91b4-70ca36b2f131", "duration": "49"}, {"streamable": {"#text": "0", "fulltrack": "0"}, "@attr": {"rank": "28"}, "name": "So Much More", "artist": {"url": "http://www.last.fm/music/Fat+Joe", "mbid": "a6a4c910-2b22-4a6f-aebe-805b176c47b8", "name": "Fat Joe"}, "url": "http://www.last.fm/music/Fat+Joe/_/So+Much+More", "mbid": "1d7ed868-6644-4ce7-8d57-97b44c0e7720", "duration": "238"}, {"streamable": {"#text": "0", "fulltrack": "0"}, "@attr": {"rank": "29"}, "name": "Candy Shop", "artist": {"url": "http://www.last.fm/music/50+Cent", "mbid": "8e68819d-71be-4e7d-b41d-f1df81b01d3f", "name": "50 Cent"}, "url": "http://www.last.fm/music/50+Cent/_/Candy+Shop", "mbid": "9c450565-8bfb-4911-84c3-35ca2218fc49", "duration": "260"}, {"streamable": {"#text": "0", "fulltrack": "0"}, "@attr": {"rank": "30"}, "name": "Round & Round", "artist": {"url": "http://www.last.fm/music/Fabolous", "mbid": "d2299099-e617-46dd-b013-ba0b4c72bc63", "name": "Fabolous"}, "url": "http://www.last.fm/music/Fabolous/_/Round+&+Round", "mbid": "3316b8cf-0192-495a-a24d-c8e4a458c88b", "duration": "113"}, {"streamable": {"#text": "0", "fulltrack": "0"}, "@attr": {"rank": "31"}, "name": "Criminal Set", "artist": {"url": "http://www.last.fm/music/Xzibit", "mbid": "9e839dc3-55f3-4492-ad0e-a1a2e84275e2", "name": "Xzibit"}, "url": "http://www.last.fm/music/Xzibit/_/Criminal+Set", "mbid": "c6fd18a2-d935-4758-9126-8bd09a78dcc3", "duration": "196"}, {"streamable": {"#text": "0", "fulltrack": "0"}, "@attr": {"rank": "32"}, "name": "Animal", "artist": {"url": "http://www.last.fm/music/50+Cent", "mbid": "8e68819d-71be-4e7d-b41d-f1df81b01d3f", "name": "50 Cent"}, "url": "http://www.last.fm/music/50+Cent/_/Animal", "mbid": "42b9c6c3-930f-4166-ab3b-598f8f150e64", "duration": "123"}, {"streamable": {"#text": "0", "fulltrack": "0"}, "@attr": {"rank": "33"}, "name": "Wait", "artist": {"url": "http://www.last.fm/music/Ying+Yang+Twins", "mbid": "2e80ba15-ec0f-4bd4-b263-7e0671f38255", "name": "Ying Yang Twins"}, "url": "http://www.last.fm/music/Ying+Yang+Twins/_/Wait", "mbid": "a4c9dbb9-75f8-431f-ac52-bc45f8591a71", "duration": "180"}, {"streamable": {"#text": "0", "fulltrack": "0"}, "@attr": {"rank": "34"}, "name": "Rocket Scratch", "artist": {"url": "http://www.last.fm/music/DJ+Rectangle", "mbid": "901fc9df-8e2f-4d9c-8e5a-d9b67afc7823", "name": "DJ Rectangle"}, "url": "http://www.last.fm/music/DJ+Rectangle/_/Rocket+Scratch", "mbid": "5afb4f4f-26c7-42ee-9840-dd7b6cd3effa", "duration": "20"}, {"streamable": {"#text": "0", "fulltrack": "0"}, "@attr": {"rank": "35"}, "name": "Thug4Life", "artist": {"url": "http://www.last.fm/music/2Pac", "mbid": "382f1005-e9ab-4684-afd4-0bdae4ee37f2", "name": "2Pac"}, "url": "http://www.last.fm/music/2Pac/_/Thug4Life", "mbid": "3cc0b815-f625-4b8c-a6a6-5ca157c57ea7", "duration": "108"}, {"streamable": {"#text": "0", "fulltrack": "0"}, "@attr": {"rank": "36"}, "name": "B*L*E*N*D (112 vs. Twista) (feat. Faith Evans)", "artist": {"url": "http://www.last.fm/music/DJ+Rectangle", "mbid": "901fc9df-8e2f-4d9c-8e5a-d9b67afc7823", "name": "DJ Rectangle"}, "url": "http://www.last.fm/music/DJ+Rectangle/_/B*L*E*N*D+(112+vs.+Twista)+(feat.+Faith+Evans)", "mbid": "89c4bd6b-c8be-40be-a172-010862713c31", "duration": "187"}, {"streamable": {"#text": "0", "fulltrack": "0"}, "@attr": {"rank": "37"}, "name": "Cherry Bomb Scratch", "artist": {"url": "http://www.last.fm/music/DJ+Rectangle", "mbid": "901fc9df-8e2f-4d9c-8e5a-d9b67afc7823", "name": "DJ Rectangle"}, "url": "http://www.last.fm/music/DJ+Rectangle/_/Cherry+Bomb+Scratch", "mbid": "378ee664-3f22-49b0-bcec-4bd6b077a9ab", "duration": "19"}, {"streamable": {"#text": "0", "fulltrack": "0"}, "@attr": {"rank": "38"}, "name": "#1Spot", "artist": {"url": "http://www.last.fm/music/Ludacris", "mbid": "0638ba22-040f-438d-83a5-9b670c4adaf5", "name": "Ludacris"}, "url": "http://www.last.fm/music/Ludacris/_/%231Spot", "mbid": "9301c639-912c-413b-ba15-2f0c20e5cbb8", "duration": "111"}, {"streamable": {"#text": "0", "fulltrack": "0"}, "@attr": {"rank": "39"}, "name": "Powder Burn Scratch", "artist": {"url": "http://www.last.fm/music/DJ+Rectangle", "mbid": "901fc9df-8e2f-4d9c-8e5a-d9b67afc7823", "name": "DJ Rectangle"}, "url": "http://www.last.fm/music/DJ+Rectangle/_/Powder+Burn+Scratch", "mbid": "11a7222f-0b46-47ae-a49d-147782552915", "duration": "26"}, {"streamable": {"#text": "0", "fulltrack": "0"}, "@attr": {"rank": "40"}, "name": "Dreams", "artist": {"url": "http://www.last.fm/music/The+Game", "mbid": "ab91c554-63b8-44b3-bba7-042f2942c896", "name": "The Game"}, "url": "http://www.last.fm/music/The+Game/_/Dreams", "mbid": "776392c8-f34f-4aec-b316-d8f22aefa272", "duration": "287"}, {"streamable": {"#text": "0", "fulltrack": "0"}, "@attr": {"rank": "41"}, "name": "What You Gon Do B*L*E*N*D", "artist": {"url": "http://www.last.fm/music/Lil+Jon", "mbid": "a95384b1-6aec-468c-ae0d-8c6daf87c4c2", "name": "Lil Jon"}, "url": "http://www.last.fm/music/Lil+Jon/_/What+You+Gon+Do+B*L*E*N*D", "mbid": "a87412fb-d7d2-4546-9399-5f497bb4a66b", "duration": "49"}, {"streamable": {"#text": "0", "fulltrack": "0"}, "@attr": {"rank": "42"}, "name": "Soldier (feat. T.I. & Lil Wayne)", "artist": {"url": "http://www.last.fm/music/Destiny%27s+Child", "mbid": "", "name": "Destiny's Child"}, "url": "http://www.last.fm/music/Destiny%27s+Child/_/Soldier+(feat.+T.I.+&+Lil+Wayne)", "mbid": "fdb23db2-a303-4dd3-b4dc-a6da1659aad8", "duration": "26"}, {"streamable": {"#text": "0", "fulltrack": "0"}, "@attr": {"rank": "43"}, "name": "Firestarter Scratch", "artist": {"url": "http://www.last.fm/music/DJ+Rectangle", "mbid": "901fc9df-8e2f-4d9c-8e5a-d9b67afc7823", "name": "DJ Rectangle"}, "url": "http://www.last.fm/music/DJ+Rectangle/_/Firestarter+Scratch", "mbid": "3fa73399-8418-4383-8ce9-bcf332d092b4", "duration": "19"}, {"streamable": {"#text": "0", "fulltrack": "0"}, "@attr": {"rank": "44"}, "name": "Shyne On (feat. Lil wayne)", "artist": {"url": "http://www.last.fm/music/Baby", "mbid": "371b80b4-7b6e-43d2-b8ef-4e4ed54ad565", "name": "Baby"}, "url": "http://www.last.fm/music/Baby/_/Shyne+On+(feat.+Lil+wayne)", "mbid": "57b90f65-290e-4006-b371-44dd66fa5aca", "duration": "90"}, {"streamable": {"#text": "0", "fulltrack": "0"}, "@attr": {"rank": "45"}, "name": "Leaning On You", "artist": {"url": "http://www.last.fm/music/Geto+Boys", "mbid": "a78ca453-3a53-4b19-8b2d-61b10dd45558", "name": "Geto Boys"}, "url": "http://www.last.fm/music/Geto+Boys/_/Leaning+On+You", "mbid": "d1004353-09e6-41a5-8b89-8e9b2e68fa11", "duration": "188"}, {"streamable": {"#text": "0", "fulltrack": "0"}, "@attr": {"rank": "46"}, "name": "Highly Flammable Scratch", "artist": {"url": "http://www.last.fm/music/DJ+Rectangle", "mbid": "901fc9df-8e2f-4d9c-8e5a-d9b67afc7823", "name": "DJ Rectangle"}, "url": "http://www.last.fm/music/DJ+Rectangle/_/Highly+Flammable+Scratch", "mbid": "0cf3e54b-ce62-4e28-abd9-5b38c8d091ef", "duration": "25"}, {"streamable": {"#text": "0", "fulltrack": "0"}, "@attr": {"rank": "47"}, "name": "Down & Out (feat. Syleena Johnson)", "artist": {"url": "http://www.last.fm/music/Cam%27ron", "mbid": "", "name": "Cam'ron"}, "url": "http://www.last.fm/music/Cam%27ron/_/Down+&+Out+(feat.+Syleena+Johnson)", "mbid": "3ca97f50-8cfe-4cae-9e65-f0d7cdab7c40", "duration": "177"}, {"streamable": {"#text": "0", "fulltrack": "0"}, "@attr": {"rank": "48"}, "name": "Freestyle", "artist": {"url": "http://www.last.fm/music/50+Cent", "mbid": "8e68819d-71be-4e7d-b41d-f1df81b01d3f", "name": "50 Cent"}, "url": "http://www.last.fm/music/50+Cent/_/Freestyle", "mbid": "d274e47c-3194-46a7-ae1a-a48fd03661d1", "duration": "34"}]}, "playcount": "546050", "id": "3637313"}}