{"album": {"name": "Twentysomething", "artist": "Jamie Cullum", "url": "http://www.last.fm/music/Jamie+Cullum/Twentysomething", "image": [{"#text": "http://userserve-ak.last.fm/serve/34s/60646763.png", "size": "small"}, {"#text": "http://userserve-ak.last.fm/serve/64s/60646763.png", "size": "medium"}, {"#text": "http://userserve-ak.last.fm/serve/174s/60646763.png", "size": "large"}, {"#text": "http://userserve-ak.last.fm/serve/300x300/60646763.png", "size": "extralarge"}, {"#text": "http://userserve-ak.last.fm/serve/_/60646763/Twentysomething.png", "size": "mega"}], "listeners": "443111", "toptags": {"tag": [{"url": "http://www.last.fm/tag/jazz", "name": "jazz"}, {"url": "http://www.last.fm/tag/albums%20i%20own", "name": "albums i own"}, {"url": "http://www.last.fm/tag/jamie%20cullum", "name": "jamie cullum"}, {"url": "http://www.last.fm/tag/singer-songwriter", "name": "singer-songwriter"}, {"url": "http://www.last.fm/tag/piano", "name": "piano"}]}, "releasedate": "    23 Nov 2004, 00:00", "mbid": "1e5a31d5-f08b-4700-bfe8-435c93f84fca", "tracks": {"track": [{"streamable": {"#text": "0", "fulltrack": "0"}, "@attr": {"rank": "1"}, "name": "What A Difference A Day Made", "artist": {"url": "http://www.last.fm/music/Jamie+Cullum", "mbid": "15f8b16a-7a0b-4a12-9f3f-e53f2451f7d7", "name": "Jamie Cullum"}, "url": "http://www.last.fm/music/Jamie+Cullum/_/What+A+Difference+A+Day+Made", "mbid": "023d39b7-ed88-40c3-881d-51b5d09c49bc", "duration": "293"}, {"streamable": {"#text": "0", "fulltrack": "0"}, "@attr": {"rank": "2"}, "name": "These Are The Days", "artist": {"url": "http://www.last.fm/music/Jamie+Cullum", "mbid": "15f8b16a-7a0b-4a12-9f3f-e53f2451f7d7", "name": "Jamie Cullum"}, "url": "http://www.last.fm/music/Jamie+Cullum/_/These+Are+The+Days", "mbid": "5cd74b44-a3c9-461a-8692-1d571ddd10e0", "duration": "201"}, {"streamable": {"#text": "0", "fulltrack": "0"}, "@attr": {"rank": "3"}, "name": "Singin' In The Rain", "artist": {"url": "http://www.last.fm/music/Jamie+Cullum", "mbid": "15f8b16a-7a0b-4a12-9f3f-e53f2451f7d7", "name": "Jamie Cullum"}, "url": "http://www.last.fm/music/Jamie+Cullum/_/Singin%27+In+The+Rain", "mbid": "11682ee2-0291-4190-bc18-3296b63dff81", "duration": "247"}, {"streamable": {"#text": "0", "fulltrack": "0"}, "@attr": {"rank": "4"}, "name": "Twentysomething", "artist": {"url": "http://www.last.fm/music/Jamie+Cullum", "mbid": "15f8b16a-7a0b-4a12-9f3f-e53f2451f7d7", "name": "Jamie Cullum"}, "url": "http://www.last.fm/music/Jamie+Cullum/_/Twentysomething", "mbid": "e3daa811-dcb6-41e3-8b72-1a3f6893644c", "duration": "220"}, {"streamable": {"#text": "0", "fulltrack": "0"}, "@attr": {"rank": "5"}, "name": "But For Now", "artist": {"url": "http://www.last.fm/music/Jamie+Cullum", "mbid": "15f8b16a-7a0b-4a12-9f3f-e53f2451f7d7", "name": "Jamie Cullum"}, "url": "http://www.last.fm/music/Jamie+Cullum/_/But+For+Now", "mbid": "0d4dd84c-5a20-420f-8ba2-162008d0c1c4", "duration": "206"}, {"streamable": {"#text": "0", "fulltrack": "0"}, "@attr": {"rank": "6"}, "name": "Old Devil Moon", "artist": {"url": "http://www.last.fm/music/Jamie+Cullum", "mbid": "15f8b16a-7a0b-4a12-9f3f-e53f2451f7d7", "name": "Jamie Cullum"}, "url": "http://www.last.fm/music/Jamie+Cullum/_/Old+Devil+Moon", "mbid": "0049fff0-232e-40cd-9835-854ec0d15747", "duration": "251"}, {"streamable": {"#text": "0", "fulltrack": "0"}, "@attr": {"rank": "7"}, "name": "I Could Have Danced All Night", "artist": {"url": "http://www.last.fm/music/Jamie+Cullum", "mbid": "15f8b16a-7a0b-4a12-9f3f-e53f2451f7d7", "name": "Jamie Cullum"}, "url": "http://www.last.fm/music/Jamie+Cullum/_/I+Could+Have+Danced+All+Night", "mbid": "1dd10c95-d08d-4daa-9188-a2865a1ceb75", "duration": "204"}, {"streamable": {"#text": "0", "fulltrack": "0"}, "@attr": {"rank": "8"}, "name": "Blame It On My Youth", "artist": {"url": "http://www.last.fm/music/Jamie+Cullum", "mbid": "15f8b16a-7a0b-4a12-9f3f-e53f2451f7d7", "name": "Jamie Cullum"}, "url": "http://www.last.fm/music/Jamie+Cullum/_/Blame+It+On+My+Youth", "mbid": "0e50fd45-a2af-4f99-a04d-74e09c9b26a8", "duration": "192"}, {"streamable": {"#text": "0", "fulltrack": "0"}, "@attr": {"rank": "9"}, "name": "I Get A Kick Out Of You", "artist": {"url": "http://www.last.fm/music/Jamie+Cullum", "mbid": "15f8b16a-7a0b-4a12-9f3f-e53f2451f7d7", "name": "Jamie Cullum"}, "url": "http://www.last.fm/music/Jamie+Cullum/_/I+Get+A+Kick+Out+Of+You", "mbid": "06a47882-b800-4684-9bc5-d17ce0e8cf66", "duration": "252"}, {"streamable": {"#text": "0", "fulltrack": "0"}, "@attr": {"rank": "10"}, "name": "All At Sea", "artist": {"url": "http://www.last.fm/music/Jamie+Cullum", "mbid": "15f8b16a-7a0b-4a12-9f3f-e53f2451f7d7", "name": "Jamie Cullum"}, "url": "http://www.last.fm/music/Jamie+Cullum/_/All+At+Sea", "mbid": "0f7cc1f6-3bc9-4bfa-bdd3-5c1ecd3fca80", "duration": "273"}, {"streamable": {"#text": "0", "fulltrack": "0"}, "@attr": {"rank": "11"}, "name": "Wind Cries Mary", "artist": {"url": "http://www.last.fm/music/Jamie+Cullum", "mbid": "15f8b16a-7a0b-4a12-9f3f-e53f2451f7d7", "name": "Jamie Cullum"}, "url": "http://www.last.fm/music/Jamie+Cullum/_/Wind+Cries+Mary", "mbid": "057686b4-e41d-4d0c-bdc2-da0d79d4f7af", "duration": "215"}, {"streamable": {"#text": "0", "fulltrack": "0"}, "@attr": {"rank": "12"}, "name": "Lover, You Should Have Come Over", "artist": {"url": "http://www.last.fm/music/Jamie+Cullum", "mbid": "15f8b16a-7a0b-4a12-9f3f-e53f2451f7d7", "name": "Jamie Cullum"}, "url": "http://www.last.fm/music/Jamie+Cullum/_/Lover,+You+Should+Have+Come+Over", "mbid": "29274ddb-0e57-493e-97f5-a83bc972e8d7", "duration": "289"}, {"streamable": {"#text": "0", "fulltrack": "0"}, "@attr": {"rank": "13"}, "name": "It's About Time", "artist": {"url": "http://www.last.fm/music/Jamie+Cullum", "mbid": "15f8b16a-7a0b-4a12-9f3f-e53f2451f7d7", "name": "Jamie Cullum"}, "url": "http://www.last.fm/music/Jamie+Cullum/_/It%27s+About+Time", "mbid": "092ef3be-a819-4104-a10c-7363c18bd156", "duration": "236"}, {"streamable": {"#text": "0", "fulltrack": "0"}, "@attr": {"rank": "14"}, "name": "Next Year Baby", "artist": {"url": "http://www.last.fm/music/Jamie+Cullum", "mbid": "15f8b16a-7a0b-4a12-9f3f-e53f2451f7d7", "name": "Jamie Cullum"}, "url": "http://www.last.fm/music/Jamie+Cullum/_/Next+Year+Baby", "mbid": "4d180ac1-a25b-4b8d-ab44-fa9b10e78e5d", "duration": "308"}, {"streamable": {"#text": "0", "fulltrack": "0"}, "@attr": {"rank": "15"}, "name": "Everlasting Love", "artist": {"url": "http://www.last.fm/music/Jamie+Cullum", "mbid": "15f8b16a-7a0b-4a12-9f3f-e53f2451f7d7", "name": "Jamie Cullum"}, "url": "http://www.last.fm/music/Jamie+Cullum/_/Everlasting+Love", "mbid": "d5a68dd9-149e-4143-a947-8ce9100bd79b", "duration": "201"}, {"streamable": {"#text": "0", "fulltrack": "0"}, "@attr": {"rank": "16"}, "name": "Frontin' (BBC Radio 1 Live Lounge Edit)", "artist": {"url": "http://www.last.fm/music/Jamie+Cullum", "mbid": "15f8b16a-7a0b-4a12-9f3f-e53f2451f7d7", "name": "Jamie Cullum"}, "url": "http://www.last.fm/music/Jamie+Cullum/_/Frontin%27+(BBC+Radio+1+Live+Lounge+Edit)", "mbid": "", "duration": "239"}, {"streamable": {"#text": "0", "fulltrack": "0"}, "@attr": {"rank": "17"}, "name": "Can't We Be Friends?", "artist": {"url": "http://www.last.fm/music/Jamie+Cullum", "mbid": "15f8b16a-7a0b-4a12-9f3f-e53f2451f7d7", "name": "Jamie Cullum"}, "url": "http://www.last.fm/music/Jamie+Cullum/_/Can%27t+We+Be+Friends%3F", "mbid": "93e9a01d-a168-45e2-8831-3fd850d8efda", "duration": "214"}, {"streamable": {"#text": "0", "fulltrack": "0"}, "@attr": {"rank": "18"}, "name": "High And Dry (South Bank Show)", "artist": {"url": "http://www.last.fm/music/Jamie+Cullum", "mbid": "15f8b16a-7a0b-4a12-9f3f-e53f2451f7d7", "name": "Jamie Cullum"}, "url": "http://www.last.fm/music/Jamie+Cullum/_/High+And+Dry+(South+Bank+Show)", "mbid": "", "duration": "334"}, {"streamable": {"#text": "0", "fulltrack": "0"}, "@attr": {"rank": "19"}, "name": "God Only Knows", "artist": {"url": "http://www.last.fm/music/Jamie+Cullum", "mbid": "15f8b16a-7a0b-4a12-9f3f-e53f2451f7d7", "name": "Jamie Cullum"}, "url": "http://www.last.fm/music/Jamie+Cullum/_/God+Only+Knows", "mbid": "4e14218f-2bdf-4325-874f-fef20a5886cf", "duration": "173"}]}, "playcount": "4130445", "id": "1413409"}}