{"streamable": {"#text": "1", "fulltrack": "0"}, "@attr": {"rank": "698"}, "name": "Homens", "artist": {"url": "http://www.last.fm/music/Manu+Chao", "mbid": "7570a0dd-5a67-401b-b19a-261eee01a284", "name": "Manu Chao"}, "url": "http://www.last.fm/music/Manu+Chao/_/Homens", "image": [{"#text": "http://userserve-ak.last.fm/serve/34s/90364327.png", "size": "small"}, {"#text": "http://userserve-ak.last.fm/serve/64s/90364327.png", "size": "medium"}, {"#text": "http://userserve-ak.last.fm/serve/126/90364327.png", "size": "large"}, {"#text": "http://userserve-ak.last.fm/serve/300x300/90364327.png", "size": "extralarge"}], "mbid": "70748db4-d9b7-4935-8ff7-560521dda869", "duration": "198"}