{"streamable": {"#text": "1", "fulltrack": "0"}, "@attr": {"rank": "362"}, "name": "I Don't Wanna Wait", "artist": {"url": "http://www.last.fm/music/SOJA", "mbid": "9e7f1111-815a-4e01-b799-24409c321e7c", "name": "SOJA"}, "url": "http://www.last.fm/music/SOJA/_/I+Don%27t+Wanna+Wait", "image": [{"#text": "http://userserve-ak.last.fm/serve/34s/36394889.jpg", "size": "small"}, {"#text": "http://userserve-ak.last.fm/serve/64s/36394889.jpg", "size": "medium"}, {"#text": "http://userserve-ak.last.fm/serve/126/36394889.jpg", "size": "large"}, {"#text": "http://userserve-ak.last.fm/serve/300x300/36394889.jpg", "size": "extralarge"}], "mbid": "", "duration": "357"}