{"track": {"album": {"@attr": {"position": "9"}, "title": "Hebron Gate", "url": "http://www.last.fm/music/Groundation/Hebron+Gate", "image": [{"#text": "http://userserve-ak.last.fm/serve/64s/32956331.jpg", "size": "small"}, {"#text": "http://userserve-ak.last.fm/serve/126/32956331.jpg", "size": "medium"}, {"#text": "http://userserve-ak.last.fm/serve/174s/32956331.jpg", "size": "large"}, {"#text": "http://userserve-ak.last.fm/serve/300x300/32956331.jpg", "size": "extralarge"}], "artist": "Groundation", "mbid": "0feac73a-6fb2-43b4-b4d0-0de742c16bfd"}, "streamable": {"#text": "0", "fulltrack": "0"}, "name": "Undivided", "artist": {"url": "http://www.last.fm/music/Groundation", "mbid": "592b9a1b-b900-4c1a-a165-bd7e7ce87d23", "name": "Groundation"}, "url": "http://www.last.fm/music/Groundation/_/Undivided", "listeners": "26195", "comments": ["Awesome song.", "comments on Groundation tracks are always so filled with positivity.\nLove y'all :D", "love it !!", "Cant help it, just love it!", "Always a conscious message!", "onelove", ":) like", "babylon jah here we come", "JAH RASTAFAR I....!!!", "divin", "Great track.", ":)))", ":)", "Pure Love.. Jah Bless You..!!!", "don carlos!!! Bless up this track", "YO POSITIVE PEOPLE!! If you like Groundation and Concious Reggae/Dancehall please check out my music. I am out of Cincinnati Ohio, concious lyrics and a message that must be heard. My last fm page is: http://www.last.fm/music/Elementree My myspace page is: http://www.myspace.com/elementree1. Jah Bless and his message forever spread!!", "just love it !!", "....andiamo..\r\nquesto e vero REGGAE..", "congratulation for this perfomance very good trio on a wonderful melody\njah jah will answer to the guardians of life", "mucha clase"], "toptags": {"tag": [{"url": "http://www.last.fm/tag/reggae", "name": "reggae"}, {"url": "http://www.last.fm/tag/dub", "name": "dub"}, {"url": "http://www.last.fm/tag/roots", "name": "roots"}, {"url": "http://www.last.fm/tag/groundation", "name": "groundation"}, {"url": "http://www.last.fm/tag/roots%20reggae", "name": "roots reggae"}]}, "mbid": "e8c7d3d7-f444-4305-a7ee-dae91e970422", "duration": "350000", "playcount": "86727", "id": "3503767"}}