{"track": {"album": {"@attr": {"position": "13"}, "title": "Shake Off the Dust... ARISE", "url": "http://www.last.fm/music/Matisyahu/Shake+Off+the+Dust...+ARISE", "image": [{"#text": "http://userserve-ak.last.fm/serve/64s/81789361.jpg", "size": "small"}, {"#text": "http://userserve-ak.last.fm/serve/126/81789361.jpg", "size": "medium"}, {"#text": "http://userserve-ak.last.fm/serve/174s/81789361.jpg", "size": "large"}, {"#text": "http://userserve-ak.last.fm/serve/300x300/81789361.jpg", "size": "extralarge"}], "artist": "Matisyahu", "mbid": ""}, "streamable": {"#text": "1", "fulltrack": "0"}, "name": "Exaltation", "artist": {"url": "http://www.last.fm/music/Matisyahu", "mbid": "c9433c4c-de33-46d4-b248-1232c34740cc", "name": "Matisyahu"}, "url": "http://www.last.fm/music/Matisyahu/_/Exaltation", "listeners": "85568", "comments": ["Diggn'  this.", "i'm so in love with this song, always makes me happy", "Marvelous song", "not bad", "loving the original version of this song.", "All the best of Matisyahu is in this song", "weno weno", "i like dis alot", "wenisimo", "this kid can still drop it like he did on the lot. keep it real brother.", "AH - SOME", "Exaltation, my God of salvation", "this kid can still drop it like he did on the lot.  keep it real brother.", "groovy", "This is awsome!", "freedom loco", "yiggi yo yo yoy", "LOVE THIS!!!", "Share teh culture", "\u0433\u0443\u0434"], "toptags": {"tag": [{"url": "http://www.last.fm/tag/reggae", "name": "reggae"}, {"url": "http://www.last.fm/tag/matisyahu", "name": "matisyahu"}, {"url": "http://www.last.fm/tag/jewish", "name": "jewish"}, {"url": "http://www.last.fm/tag/jewish%20reggae", "name": "jewish reggae"}, {"url": "http://www.last.fm/tag/hip-hop", "name": "hip-hop"}]}, "mbid": "ec8917fd-2712-466d-8bea-f36fa4ed1704", "duration": "304000", "playcount": "367763", "id": "10484794"}}