{"streamable": {"#text": "0", "fulltrack": "0"}, "@attr": {"rank": "13"}, "name": "Tears in Heaven", "artist": {"url": "http://www.last.fm/music/Eric+Clapton", "mbid": "05c35c95-dcbd-4492-b091-7f05a2091d47", "name": "Eric Clapton"}, "url": "http://www.last.fm/music/Eric+Clapton/_/Tears+in+Heaven", "image": [{"#text": "http://userserve-ak.last.fm/serve/34s/54535385.jpg", "size": "small"}, {"#text": "http://userserve-ak.last.fm/serve/64s/54535385.jpg", "size": "medium"}, {"#text": "http://userserve-ak.last.fm/serve/126/54535385.jpg", "size": "large"}, {"#text": "http://userserve-ak.last.fm/serve/300x300/54535385.jpg", "size": "extralarge"}], "mbid": "01354bd4-4fab-465c-a1c2-beec2579607e", "duration": "271"}