{"streamable": {"#text": "0", "fulltrack": "0"}, "@attr": {"rank": "935"}, "name": "All Your Love (I Miss Loving)", "artist": {"url": "http://www.last.fm/music/Otis+Rush", "mbid": "40ee7c92-f44a-4d14-9aee-f87244465ee4", "name": "Otis Rush"}, "url": "http://www.last.fm/music/Otis+Rush/_/All+Your+Love+(I+Miss+Loving)", "image": [{"#text": "http://userserve-ak.last.fm/serve/34s/19296653.jpg", "size": "small"}, {"#text": "http://userserve-ak.last.fm/serve/64s/19296653.jpg", "size": "medium"}, {"#text": "http://userserve-ak.last.fm/serve/126/19296653.jpg", "size": "large"}, {"#text": "http://userserve-ak.last.fm/serve/300x300/19296653.jpg", "size": "extralarge"}], "mbid": "9544a45e-dc4d-4279-8482-ce3824f120cc", "duration": "536"}