{"streamable": {"#text": "0", "fulltrack": "0"}, "@attr": {"rank": "67"}, "name": "Ten Long Years", "artist": {"url": "http://www.last.fm/music/B.B.+King+&+Eric+Clapton", "mbid": "", "name": "B.B. King & Eric Clapton"}, "url": "http://www.last.fm/music/B.B.+King+&+Eric+Clapton/_/Ten+Long+Years", "image": [{"#text": "http://userserve-ak.last.fm/serve/34s/66596948.jpg", "size": "small"}, {"#text": "http://userserve-ak.last.fm/serve/64s/66596948.jpg", "size": "medium"}, {"#text": "http://userserve-ak.last.fm/serve/126/66596948.jpg", "size": "large"}, {"#text": "http://userserve-ak.last.fm/serve/300x300/66596948.jpg", "size": "extralarge"}], "mbid": "a8f52695-7a39-4d12-aed1-3c7627265d1e", "duration": "280"}